jalansim/__init__.py
jalansim/_core_cpu.cpython-312-x86_64-linux-gnu.so
jalansim/_core_cuda.cpython-312-x86_64-linux-gnu.so
jalansim/configs/f1tenth.py
jalansim/configs/jackal.py
jalansim.libs/libgomp-a34b3233.so.1.0.0
jalansim-0.0.1.dist-info/METADATA
jalansim-0.0.1.dist-info/WHEEL
jalansim-0.0.1.dist-info/RECORD
