Metadata-Version: 2.2
Name: jalansim
Version: 0.0.1
Summary: GPU-accelerated 2D navigation simulator.
Author-Email: "Joshua J. Damanik" <joshuajdmk@gmail.com>
Project-URL: Homepage, https://github.com/damanikjosh/jalansim
Requires-Python: <=3.13,>=3.8
